setup.py
riak_docs.egg-info/PKG-INFO
riak_docs.egg-info/SOURCES.txt
riak_docs.egg-info/dependency_links.txt
riak_docs.egg-info/requires.txt
riak_docs.egg-info/top_level.txt
riakdoc/__init__.py
riakdoc/documents.py
riakdoc/indexes.py
riakdoc/keygen.py
riakdoc/settings.py
riakdoc/tests.py