Metadata-Version: 1.0
Name: riak-docs
Version: 0.1.7
Summary: Models to facilitate some common interactions with Riak documents.
Home-page: https://bitbucket.org/danostrowski/riakdocs
Author: Dan Ostrowski
Author-email: dan.ostrowski@gmail.com
License: BSD
Keywords: riak models object
Platform: UNKNOWN
Classifier: Programming Language :: Python :: 2.5
Classifier: Programming Language :: Python :: 2.6
Classifier: Programming Language :: Python :: 2.7
Classifier: Development Status :: 3 - Alpha
Classifier: License :: OSI Approved :: MIT License
Classifier: Intended Audience :: Developers
Classifier: Topic :: Database
Classifier: Topic :: Software Development :: Libraries :: Python Modules
